appium78/__init__.py
appium78/appium78.py
appium78/main.py
appium78-0.1.9.dist-info/LICENSE
appium78-0.1.9.dist-info/METADATA
appium78-0.1.9.dist-info/WHEEL
appium78-0.1.9.dist-info/RECORD
