Metadata-Version: 2.1
Name: appium78
Version: 0.1.9
Summary: A Python wrapper for Appium
Author: Frieda.Hu
Author-email: www778878net@189.cn
Requires-Python: >=3.12,<4.0
Classifier: Programming Language :: Python :: 3
Classifier: Programming Language :: Python :: 3.12
Requires-Dist: appium-python-client (>=2.11.0,<3.0.0)
